match_series_batch/__init__.py
match_series_batch/config.py
match_series_batch/main.py
match_series_batch/processing.py
match_series_batch/utils.py
match_series_batch-1.2.1.dist-info/LICENSE
match_series_batch-1.2.1.dist-info/METADATA
match_series_batch-1.2.1.dist-info/WHEEL
match_series_batch-1.2.1.dist-info/entry_points.txt
match_series_batch-1.2.1.dist-info/top_level.txt
match_series_batch-1.2.1.dist-info/RECORD
