Metadata-Version: 2.1
Name: match-series-batch
Version: 1.2.1
Summary: Batch non-rigid image registration with NLMeans or NLPCA denoising and stage average output.
Home-page: https://github.com/HaoranLMaoMao/match-series-batch
Author: Haoran Ma
Author-email: haoran.ma@ikz-berlin.de
Classifier: Programming Language :: Python :: 3
Classifier: License :: OSI Approved :: MIT License
Classifier: Operating System :: OS Independent
Requires-Python: >=3.7
License-File: LICENSE
Requires-Dist: hyperspy>=1.6.1
Requires-Dist: pymatchseries>=0.1.0
Requires-Dist: tqdm
Requires-Dist: Pillow
Requires-Dist: scikit-image
Requires-Dist: scikit-learn
